lentil/__init__.py
lentil/convolvable.py
lentil/detector.py
lentil/extent.py
lentil/field.py
lentil/fourier.py
lentil/helper.py
lentil/plane.py
lentil/propagate.py
lentil/ptype.py
lentil/radiometry.py
lentil/segmented.py
lentil/shape.py
lentil/util.py
lentil/wavefront.py
lentil/wfe.py
lentil/zernike.py
lentil-0.8.7.dist-info/licenses/LICENSE.rst
lentil-0.8.7.dist-info/METADATA
lentil-0.8.7.dist-info/WHEEL
lentil-0.8.7.dist-info/top_level.txt
lentil-0.8.7.dist-info/RECORD
