Metadata-Version: 2.4
Name: lentil
Version: 0.8.7
Summary: Heart-healthy physical optics
Author: Andy Kee
License: Copyright (c) 2020-2023, California Institute of Technology ("Caltech"). 
Project-URL: Homepage, https://github.com/andykee/lentil
Project-URL: Documentation, https://andykee.github.io/lentil/
Project-URL: Bug Tracker, https://github.com/andykee/lentil/issues
Classifier: Development Status :: 4 - Beta
Classifier: Intended Audience :: Science/Research
Classifier: License :: OSI Approved :: BSD License
Classifier: Programming Language :: Python :: 3
Classifier: Topic :: Scientific/Engineering
Classifier: Topic :: Scientific/Engineering :: Astronomy
Classifier: Topic :: Scientific/Engineering :: Physics
Requires-Python: >=3.8
License-File: LICENSE.rst
Requires-Dist: numpy>=1.17
Requires-Dist: scipy
Dynamic: license-file
